{
  "task": "T-MLR-2.3",
  "timestamp": "2025-10-22T18:36:02.376939Z",
  "description": "Train models on all 20 synthetic tenants with cross-validation",
  "config": {
    "n_folds": 5,
    "num_tenants": 20
  },
  "aggregate_metrics": {
    "num_tenants": 20,
    "num_folds": 5,
    "mean_r2_across_tenants": 0.10955439121289565,
    "std_r2_across_tenants": 0.23507116573647951,
    "mean_rmse_across_tenants": 1929.9853898379392,
    "mean_mae_across_tenants": 1600.9074641888965,
    "best_tenant_r2": 0.7126684198074439,
    "worst_tenant_r2": -0.013153525200253535,
    "num_passing": 3,
    "pass_rate": 0.15
  },
  "results": {
    "extreme_cooling": {
      "model_name": "extreme_cooling",
      "num_folds": 5,
      "mean_r2": -0.003832615189187344,
      "std_r2": 0.003883791888327328,
      "mean_rmse": 7360.679776779837,
      "mean_mae": 6392.073259775325,
      "fold_r2_scores": [
        0.0022968775147192977,
        -0.005095794234341033,
        -0.008425465435151658,
        -0.004106078601975982
      ],
      "fold_rmse_scores": [
        7415.088687345039,
        7430.799564507613,
        7256.285891575472,
        7340.544963691224
      ],
      "fold_mae_scores": [
        6434.233526037371,
        6491.237354104466,
        6294.951508511926,
        6347.870650447533
      ],
      "weather_elasticity": {
        "temperature": [
          101.4209251067935,
          92.8541428906855,
          67.22699856168558,
          55.640261144209546
        ],
        "humidity": [
          -117.31023869395548,
          -100.85901802088883,
          -74.05258357088002,
          -56.14195681359657
        ],
        "precipitation": [
          -353.6351186889438,
          -232.25611834944272,
          -104.84117211111052,
          -109.13069387603093
        ]
      },
      "channel_roas": {
        "meta_spend": [
          -31.08142238016567,
          23.842534315743606,
          28.87892604959786,
          -1.8724607261803001
        ],
        "google_spend": [
          -26.002756658109313,
          54.073702700367406,
          31.97227658438262,
          -56.127642205681276
        ]
      },
      "fold_details": [
        {
          "fold": 1,
          "train_size": 1095,
          "test_size": 1095,
          "r2": 0.0022968775147192977,
          "rmse": 7415.088687345039,
          "mae": 6434.233526037371
        },
        {
          "fold": 2,
          "train_size": 2190,
          "test_size": 1095,
          "r2": -0.005095794234341033,
          "rmse": 7430.799564507613,
          "mae": 6491.237354104466
        },
        {
          "fold": 3,
          "train_size": 3285,
          "test_size": 1095,
          "r2": -0.008425465435151658,
          "rmse": 7256.285891575472,
          "mae": 6294.951508511926
        },
        {
          "fold": 4,
          "train_size": 4380,
          "test_size": 1095,
          "r2": -0.004106078601975982,
          "rmse": 7340.544963691224,
          "mae": 6347.870650447533
        }
      ]
    },
    "extreme_heating": {
      "model_name": "extreme_heating",
      "num_folds": 5,
      "mean_r2": 0.15576305739747084,
      "std_r2": 0.1517950159940875,
      "mean_rmse": 240.41037438569023,
      "mean_mae": 180.53420529878625,
      "fold_r2_scores": [
        0.2786409438802726,
        -0.021516649203722205,
        0.03437046297649271,
        0.33155747193684026
      ],
      "fold_rmse_scores": [
        304.5133993035922,
        208.95983456795992,
        202.07005804753874,
        246.0982056236701
      ],
      "fold_mae_scores": [
        189.21412297571652,
        176.80799532266835,
        168.74485365047613,
        187.36984924628405
      ],
      "weather_elasticity": {
        "temperature": [
          -2.1424154671399496,
          11.924372265157446,
          11.99599467634778,
          12.084215736308616
        ],
        "humidity": [
          -1.7065207949270285,
          -17.58631232597223,
          -17.159494300538334,
          -17.29481714248518
        ],
        "precipitation": [
          -4.70101066532674,
          -8.955507845672738,
          -6.27377533117234,
          -4.766581477834125
        ]
      },
      "channel_roas": {
        "meta_spend": [
          -19.45297107190548,
          96.1315337363407,
          102.68279174168597,
          83.83753583390104
        ],
        "google_spend": [
          -4.35889522719477,
          -224.6460294862346,
          -239.7014068158727,
          -211.0282850629372
        ]
      },
      "fold_details": [
        {
          "fold": 1,
          "train_size": 1095,
          "test_size": 1095,
          "r2": 0.2786409438802726,
          "rmse": 304.5133993035922,
          "mae": 189.21412297571652
        },
        {
          "fold": 2,
          "train_size": 2190,
          "test_size": 1095,
          "r2": -0.021516649203722205,
          "rmse": 208.95983456795992,
          "mae": 176.80799532266835
        },
        {
          "fold": 3,
          "train_size": 3285,
          "test_size": 1095,
          "r2": 0.03437046297649271,
          "rmse": 202.07005804753874,
          "mae": 168.74485365047613
        },
        {
          "fold": 4,
          "train_size": 4380,
          "test_size": 1095,
          "r2": 0.33155747193684026,
          "rmse": 246.0982056236701,
          "mae": 187.36984924628405
        }
      ]
    },
    "extreme_rain_gear": {
      "model_name": "extreme_rain_gear",
      "num_folds": 5,
      "mean_r2": 0.7126684198074439,
      "std_r2": 0.08749125492241673,
      "mean_rmse": 4459.448196289608,
      "mean_mae": 3053.731143282386,
      "fold_r2_scores": [
        0.564486649819057,
        0.7374459105915332,
        0.7890812643924331,
        0.7596598544267521
      ],
      "fold_rmse_scores": [
        5449.454182046314,
        4440.8588423916735,
        4056.9924067895163,
        3890.487353930932
      ],
      "fold_mae_scores": [
        3379.882296693028,
        3152.9355338081477,
        2889.5715272878065,
        2792.5352153405624
      ],
      "weather_elasticity": {
        "temperature": [
          -63.81619289197539,
          -18.381902074326966,
          -5.671623579145827,
          -14.672035529127516
        ],
        "humidity": [
          -20.99380961431338,
          -116.06061843751488,
          -129.00877143741704,
          -113.06816613786715
        ],
        "precipitation": [
          1070.119839453138,
          1026.0175429776614,
          1122.8979041882608,
          1228.5713447371083
        ]
      },
      "channel_roas": {
        "meta_spend": [
          30.593495137834868,
          56.0096657833361,
          123.79073928550243,
          69.78011198774058
        ],
        "google_spend": [
          -88.41066493367921,
          -39.91064981921316,
          -60.229787221660466,
          -23.37971739222719
        ]
      },
      "fold_details": [
        {
          "fold": 1,
          "train_size": 1095,
          "test_size": 1095,
          "r2": 0.564486649819057,
          "rmse": 5449.454182046314,
          "mae": 3379.882296693028
        },
        {
          "fold": 2,
          "train_size": 2190,
          "test_size": 1095,
          "r2": 0.7374459105915332,
          "rmse": 4440.8588423916735,
          "mae": 3152.9355338081477
        },
        {
          "fold": 3,
          "train_size": 3285,
          "test_size": 1095,
          "r2": 0.7890812643924331,
          "rmse": 4056.9924067895163,
          "mae": 2889.5715272878065
        },
        {
          "fold": 4,
          "train_size": 4380,
          "test_size": 1095,
          "r2": 0.7596598544267521,
          "rmse": 3890.487353930932,
          "mae": 2792.5352153405624
        }
      ]
    },
    "extreme_ski_gear": {
      "model_name": "extreme_ski_gear",
      "num_folds": 5,
      "mean_r2": 0.033998561339191935,
      "std_r2": 0.02048429784135153,
      "mean_rmse": 203.87078578257268,
      "mean_mae": 172.1307536311919,
      "fold_r2_scores": [
        0.008966823840631855,
        0.06603110822167102,
        0.031288164312629374,
        0.02970814898183549
      ],
      "fold_rmse_scores": [
        207.10195378530778,
        205.0279849940786,
        203.11851597216602,
        200.23468837873827
      ],
      "fold_mae_scores": [
        175.70450062464792,
        171.14274396906012,
        173.55012847248233,
        168.12564145857726
      ],
      "weather_elasticity": {
        "temperature": [
          -4.570866453353721,
          -4.3771651888205465,
          -3.992400818180041,
          -3.8420701759838227
        ],
        "humidity": [
          0.5068969685767563,
          1.5309160683112961,
          0.6766373318950395,
          0.6343025040259591
        ],
        "precipitation": [
          -3.186768481269843,
          -10.769433203080073,
          -9.684383134276166,
          -6.190687535093187
        ]
      },
      "channel_roas": {
        "meta_spend": [
          51.03457471561022,
          -3.45055239449406,
          10.745814238558877,
          17.01217709334856
        ],
        "google_spend": [
          81.6884981721255,
          5.647336822336458,
          7.413487032583737,
          61.27726887363784
        ]
      },
      "fold_details": [
        {
          "fold": 1,
          "train_size": 1095,
          "test_size": 1095,
          "r2": 0.008966823840631855,
          "rmse": 207.10195378530778,
          "mae": 175.70450062464792
        },
        {
          "fold": 2,
          "train_size": 2190,
          "test_size": 1095,
          "r2": 0.06603110822167102,
          "rmse": 205.0279849940786,
          "mae": 171.14274396906012
        },
        {
          "fold": 3,
          "train_size": 3285,
          "test_size": 1095,
          "r2": 0.031288164312629374,
          "rmse": 203.11851597216602,
          "mae": 173.55012847248233
        },
        {
          "fold": 4,
          "train_size": 4380,
          "test_size": 1095,
          "r2": 0.02970814898183549,
          "rmse": 200.23468837873827,
          "mae": 168.12564145857726
        }
      ]
    },
    "extreme_sunscreen": {
      "model_name": "extreme_sunscreen",
      "num_folds": 5,
      "mean_r2": -0.00764913433271977,
      "std_r2": 0.005865155850642576,
      "mean_rmse": 7351.465967937171,
      "mean_mae": 6350.394410232473,
      "fold_r2_scores": [
        -0.009781895727848822,
        -0.006455316491196905,
        -0.015278598686779388,
        0.0009192735749460335
      ],
      "fold_rmse_scores": [
        7278.034952930955,
        7523.079480236112,
        7261.588675119428,
        7343.160763462187
      ],
      "fold_mae_scores": [
        6208.129570020803,
        6529.058824480081,
        6223.6846821876015,
        6440.704564241405
      ],
      "weather_elasticity": {
        "temperature": [
          7.50779493353899,
          22.015907767212873,
          51.07744591733781,
          -12.105810770403648
        ],
        "humidity": [
          -11.092791266961294,
          -48.94334021626832,
          -66.19666348247938,
          20.26257469702443
        ],
        "precipitation": [
          -103.67007035522222,
          47.033548148844076,
          -311.1707376375181,
          -218.04845511594874
        ]
      },
      "channel_roas": {
        "meta_spend": [
          2.0765368142484126,
          52.51501887242632,
          -9.180434434303208,
          -8.778361727754767
        ],
        "google_spend": [
          -2.5974948869152463,
          30.466842538254948,
          -55.96492445600962,
          -72.54001453970727
        ]
      },
      "fold_details": [
        {
          "fold": 1,
          "train_size": 1095,
          "test_size": 1095,
          "r2": -0.009781895727848822,
          "rmse": 7278.034952930955,
          "mae": 6208.129570020803
        },
        {
          "fold": 2,
          "train_size": 2190,
          "test_size": 1095,
          "r2": -0.006455316491196905,
          "rmse": 7523.079480236112,
          "mae": 6529.058824480081
        },
        {
          "fold": 3,
          "train_size": 3285,
          "test_size": 1095,
          "r2": -0.015278598686779388,
          "rmse": 7261.588675119428,
          "mae": 6223.6846821876015
        },
        {
          "fold": 4,
          "train_size": 4380,
          "test_size": 1095,
          "r2": 0.0009192735749460335,
          "rmse": 7343.160763462187,
          "mae": 6440.704564241405
        }
      ]
    },
    "high_gym_activity": {
      "model_name": "high_gym_activity",
      "num_folds": 5,
      "mean_r2": -0.00658633380608542,
      "std_r2": 0.00614564151101219,
      "mean_rmse": 3519.4582541542145,
      "mean_mae": 3049.6612248468964,
      "fold_r2_scores": [
        -0.016685103275034585,
        -0.006336798833991519,
        -0.0011496053630890568,
        -0.0021738277522265204
      ],
      "fold_rmse_scores": [
        3562.7609295095867,
        3467.3516084863586,
        3511.914682679129,
        3535.805795941784
      ],
      "fold_mae_scores": [
        3080.805134657554,
        2998.2068530978127,
        3037.441269028973,
        3082.191642603247
      ],
      "weather_elasticity": {
        "temperature": [
          -84.0547543709584,
          -33.921580022112444,
          -34.103154434467015,
          -47.439448375723515
        ],
        "humidity": [
          83.656300442919,
          41.10913274281572,
          42.43832727725068,
          56.86475506197609
        ],
        "precipitation": [
          155.6345354130358,
          32.44355643057276,
          -81.03180558984562,
          -33.56044627736341
        ]
      },
      "channel_roas": {
        "meta_spend": [
          -16.26908520302519,
          -27.533060193648566,
          11.605291190489357,
          -2.1772667183157512
        ],
        "google_spend": [
          -38.7376995850014,
          -67.25695450220624,
          2.751467872769225,
          -22.351529794000253
        ]
      },
      "fold_details": [
        {
          "fold": 1,
          "train_size": 1095,
          "test_size": 1095,
          "r2": -0.016685103275034585,
          "rmse": 3562.7609295095867,
          "mae": 3080.805134657554
        },
        {
          "fold": 2,
          "train_size": 2190,
          "test_size": 1095,
          "r2": -0.006336798833991519,
          "rmse": 3467.3516084863586,
          "mae": 2998.2068530978127
        },
        {
          "fold": 3,
          "train_size": 3285,
          "test_size": 1095,
          "r2": -0.0011496053630890568,
          "rmse": 3511.914682679129,
          "mae": 3037.441269028973
        },
        {
          "fold": 4,
          "train_size": 4380,
          "test_size": 1095,
          "r2": -0.0021738277522265204,
          "rmse": 3535.805795941784,
          "mae": 3082.191642603247
        }
      ]
    },
    "high_outdoor_gear": {
      "model_name": "high_outdoor_gear",
      "num_folds": 5,
      "mean_r2": 0.5896164118891523,
      "std_r2": 0.040665954124914756,
      "mean_rmse": 3889.0611695746447,
      "mean_mae": 3187.679157226379,
      "fold_r2_scores": [
        0.5198899332269433,
        0.6045811648364141,
        0.6208528123560317,
        0.6131417371372196
      ],
      "fold_rmse_scores": [
        4153.04515886422,
        3910.2177720248587,
        3753.227122600316,
        3739.754624809183
      ],
      "fold_mae_scores": [
        3434.582681727457,
        3181.896992541442,
        3026.0521336046254,
        3108.1848210319918
      ],
      "weather_elasticity": {
        "temperature": [
          -110.46991907815011,
          -31.9718966843234,
          -23.075086205013708,
          -28.910381388566115
        ],
        "humidity": [
          -46.80443244946667,
          -109.12535335349763,
          -115.96764240545066,
          -110.32996274160153
        ],
        "precipitation": [
          91.19792654944058,
          -115.94138024555386,
          -107.24014509148077,
          -95.40703544358242
        ]
      },
      "channel_roas": {
        "meta_spend": [
          53.533864221498874,
          135.35211531538118,
          88.95933988298533,
          135.61204270745367
        ],
        "google_spend": [
          205.35943727671798,
          242.26921770256845,
          209.0985533170955,
          223.70638904595637
        ]
      },
      "fold_details": [
        {
          "fold": 1,
          "train_size": 1095,
          "test_size": 1095,
          "r2": 0.5198899332269433,
          "rmse": 4153.04515886422,
          "mae": 3434.582681727457
        },
        {
          "fold": 2,
          "train_size": 2190,
          "test_size": 1095,
          "r2": 0.6045811648364141,
          "rmse": 3910.2177720248587,
          "mae": 3181.896992541442
        },
        {
          "fold": 3,
          "train_size": 3285,
          "test_size": 1095,
          "r2": 0.6208528123560317,
          "rmse": 3753.227122600316,
          "mae": 3026.0521336046254
        },
        {
          "fold": 4,
          "train_size": 4380,
          "test_size": 1095,
          "r2": 0.6131417371372196,
          "rmse": 3739.754624809183,
          "mae": 3108.1848210319918
        }
      ]
    },
    "high_summer_clothing": {
      "model_name": "high_summer_clothing",
      "num_folds": 5,
      "mean_r2": -0.0038383823440531484,
      "std_r2": 0.001902440666634146,
      "mean_rmse": 3509.1108332865274,
      "mean_mae": 3031.746206937219,
      "fold_r2_scores": [
        -0.004306672337485162,
        -0.005338520446088291,
        -0.0006102813190393963,
        -0.005098055273599744
      ],
      "fold_rmse_scores": [
        3576.4345071562843,
        3457.9948050660255,
        3583.6917157490852,
        3418.322305174714
      ],
      "fold_mae_scores": [
        3087.3575311333993,
        2962.681331474429,
        3135.296888775461,
        2941.649076365587
      ],
      "weather_elasticity": {
        "temperature": [
          30.807494476536053,
          70.32401021547761,
          60.23319209035402,
          42.9459481623519
        ],
        "humidity": [
          -57.862230428006264,
          -90.73275439969083,
          -88.32470233805667,
          -66.69455289490162
        ],
        "precipitation": [
          -14.443500354588657,
          -123.80633874472858,
          -7.491002783784663,
          -8.215746088054981
        ]
      },
      "channel_roas": {
        "meta_spend": [
          -0.038997528056919584,
          18.72128097512656,
          -21.59282276617327,
          -50.795653124985684
        ],
        "google_spend": [
          0.3755358250712383,
          67.15645766836874,
          15.402078046707098,
          -63.92046750916409
        ]
      },
      "fold_details": [
        {
          "fold": 1,
          "train_size": 1095,
          "test_size": 1095,
          "r2": -0.004306672337485162,
          "rmse": 3576.4345071562843,
          "mae": 3087.3575311333993
        },
        {
          "fold": 2,
          "train_size": 2190,
          "test_size": 1095,
          "r2": -0.005338520446088291,
          "rmse": 3457.9948050660255,
          "mae": 2962.681331474429
        },
        {
          "fold": 3,
          "train_size": 3285,
          "test_size": 1095,
          "r2": -0.0006102813190393963,
          "rmse": 3583.6917157490852,
          "mae": 3135.296888775461
        },
        {
          "fold": 4,
          "train_size": 4380,
          "test_size": 1095,
          "r2": -0.005098055273599744,
          "rmse": 3418.322305174714,
          "mae": 2941.649076365587
        }
      ]
    },
    "high_umbrella_rain": {
      "model_name": "high_umbrella_rain",
      "num_folds": 5,
      "mean_r2": 0.6733725556742124,
      "std_r2": 0.06004600331859387,
      "mean_rmse": 2248.0514292984544,
      "mean_mae": 1609.613121069666,
      "fold_r2_scores": [
        0.5797986516797029,
        0.747286292559623,
        0.6810217032338148,
        0.685383575223709
      ],
      "fold_rmse_scores": [
        2574.209574706369,
        2058.0488527089005,
        2230.9471551274437,
        2129.000134651104
      ],
      "fold_mae_scores": [
        1738.9220621381617,
        1557.3289340445997,
        1582.4273354072009,
        1559.774152688702
      ],
      "weather_elasticity": {
        "temperature": [
          -39.915861959663225,
          -6.53544810479895,
          -9.185475216211653,
          -21.098103411542226
        ],
        "humidity": [
          -4.786906202077407,
          -52.365538725444985,
          -48.33584142380577,
          -39.60843328022892
        ],
        "precipitation": [
          939.1762766369543,
          904.4318598859353,
          892.6538998656753,
          852.4281055373856
        ]
      },
      "channel_roas": {
        "meta_spend": [
          7.004360517846297,
          -34.33896111882589,
          -28.385376613290198,
          -31.072141985279764
        ],
        "google_spend": [
          -18.196363954324802,
          89.39125852832821,
          25.0431028524315,
          86.63017549290603
        ]
      },
      "fold_details": [
        {
          "fold": 1,
          "train_size": 1095,
          "test_size": 1095,
          "r2": 0.5797986516797029,
          "rmse": 2574.209574706369,
          "mae": 1738.9220621381617
        },
        {
          "fold": 2,
          "train_size": 2190,
          "test_size": 1095,
          "r2": 0.747286292559623,
          "rmse": 2058.0488527089005,
          "mae": 1557.3289340445997
        },
        {
          "fold": 3,
          "train_size": 3285,
          "test_size": 1095,
          "r2": 0.6810217032338148,
          "rmse": 2230.9471551274437,
          "mae": 1582.4273354072009
        },
        {
          "fold": 4,
          "train_size": 4380,
          "test_size": 1095,
          "r2": 0.685383575223709,
          "rmse": 2129.000134651104,
          "mae": 1559.774152688702
        }
      ]
    },
    "high_winter_clothing": {
      "model_name": "high_winter_clothing",
      "num_folds": 5,
      "mean_r2": 0.10135640919229488,
      "std_r2": 0.15577956303301677,
      "mean_rmse": 191.46591997599324,
      "mean_mae": 140.5214725251146,
      "fold_r2_scores": [
        0.02286527713910136,
        0.22338858487426372,
        -0.11415165168231511,
        0.27332342643812957
      ],
      "fold_rmse_scores": [
        157.3624289978989,
        236.18224476519129,
        166.50484993588142,
        205.81415620500135
      ],
      "fold_mae_scores": [
        127.39295863282662,
        150.94606935412966,
        136.67845637055038,
        147.06840574295174
      ],
      "weather_elasticity": {
        "temperature": [
          -4.209109794738948,
          -1.5045082732286224,
          3.799671295932791,
          4.785292392953752
        ],
        "humidity": [
          1.2109550933934725,
          -1.8721315496719144,
          -6.556752517125661,
          -7.577657660545681
        ],
        "precipitation": [
          1.2491381172811156,
          -7.055615355772656,
          -31.519590166979615,
          -20.768550264779492
        ]
      },
      "channel_roas": {
        "meta_spend": [
          -53.315049302968234,
          -16.69405923171117,
          -341.268085657261,
          -309.32596757176424
        ],
        "google_spend": [
          -25.31470400412233,
          -72.67712552430837,
          168.0343610349465,
          73.340771381031
        ]
      },
      "fold_details": [
        {
          "fold": 1,
          "train_size": 1095,
          "test_size": 1095,
          "r2": 0.02286527713910136,
          "rmse": 157.3624289978989,
          "mae": 127.39295863282662
        },
        {
          "fold": 2,
          "train_size": 2190,
          "test_size": 1095,
          "r2": 0.22338858487426372,
          "rmse": 236.18224476519129,
          "mae": 150.94606935412966
        },
        {
          "fold": 3,
          "train_size": 3285,
          "test_size": 1095,
          "r2": -0.11415165168231511,
          "rmse": 166.50484993588142,
          "mae": 136.67845637055038
        },
        {
          "fold": 4,
          "train_size": 4380,
          "test_size": 1095,
          "r2": 0.27332342643812957,
          "rmse": 205.81415620500135,
          "mae": 147.06840574295174
        }
      ]
    },
    "medium_accessories": {
      "model_name": "medium_accessories",
      "num_folds": 5,
      "mean_r2": -0.0026297726292515977,
      "std_r2": 0.0077380866022188095,
      "mean_rmse": 612.0442194156986,
      "mean_mae": 526.9498226364315,
      "fold_r2_scores": [
        -0.015888582027753007,
        0.0024626848552474767,
        0.0029430568721799943,
        -3.6250216680855374e-05
      ],
      "fold_rmse_scores": [
        609.3757332458234,
        603.4259941084781,
        603.8005060853047,
        631.5746442231886
      ],
      "fold_mae_scores": [
        521.4566817988299,
        513.9789338701,
        521.8094314870934,
        550.5542433897026
      ],
      "weather_elasticity": {
        "temperature": [
          10.232697240868305,
          -0.7924289795848691,
          -3.7956679051467983,
          -4.0549246851710175
        ],
        "humidity": [
          -13.219015391783225,
          -0.43859574167805276,
          2.320912858009898,
          2.500766828242231
        ],
        "precipitation": [
          0.5468028413037823,
          -5.84804725839476,
          -16.932113252993563,
          -20.25750995543302
        ]
      },
      "channel_roas": {
        "meta_spend": [
          24.76234064608747,
          -7.868591376311083,
          -15.678482696834871,
          9.60305865009736
        ],
        "google_spend": [
          53.48964266395437,
          16.681522812234583,
          19.703004897931347,
          80.76035673137221
        ]
      },
      "fold_details": [
        {
          "fold": 1,
          "train_size": 1095,
          "test_size": 1095,
          "r2": -0.015888582027753007,
          "rmse": 609.3757332458234,
          "mae": 521.4566817988299
        },
        {
          "fold": 2,
          "train_size": 2190,
          "test_size": 1095,
          "r2": 0.0024626848552474767,
          "rmse": 603.4259941084781,
          "mae": 513.9789338701
        },
        {
          "fold": 3,
          "train_size": 3285,
          "test_size": 1095,
          "r2": 0.0029430568721799943,
          "rmse": 603.8005060853047,
          "mae": 521.8094314870934
        },
        {
          "fold": 4,
          "train_size": 4380,
          "test_size": 1095,
          "r2": -3.6250216680855374e-05,
          "rmse": 631.5746442231886,
          "mae": 550.5542433897026
        }
      ]
    },
    "medium_beauty": {
      "model_name": "medium_beauty",
      "num_folds": 5,
      "mean_r2": -0.008166376678020837,
      "std_r2": 0.008758484367599757,
      "mean_rmse": 614.2130792985641,
      "mean_mae": 528.2799249853203,
      "fold_r2_scores": [
        -0.022949609998285103,
        -0.006255839082627723,
        -0.0007821615377934243,
        -0.0026778960933770968
      ],
      "fold_rmse_scores": [
        608.7570686464694,
        627.3562663646554,
        608.5947961924718,
        612.1441859906598
      ],
      "fold_mae_scores": [
        518.5735452626152,
        538.6553301433236,
        523.6682561188305,
        532.2225684165123
      ],
      "weather_elasticity": {
        "temperature": [
          -13.993425361947391,
          -3.0341219113517783,
          -2.2125393558370425,
          -1.7725933240468865
        ],
        "humidity": [
          19.664312419303446,
          2.518800186401732,
          1.8341546656189642,
          0.7815080526517422
        ],
        "precipitation": [
          8.34513047854333,
          2.2603169762887605,
          -10.032157517667597,
          -4.3898942165714265
        ]
      },
      "channel_roas": {
        "meta_spend": [
          -20.558099219951007,
          22.59246477908858,
          1.4273185619472295,
          28.793420811920974
        ],
        "google_spend": [
          -48.52126449161415,
          21.543882532892194,
          -57.029392780095854,
          -44.73877186025906
        ]
      },
      "fold_details": [
        {
          "fold": 1,
          "train_size": 1095,
          "test_size": 1095,
          "r2": -0.022949609998285103,
          "rmse": 608.7570686464694,
          "mae": 518.5735452626152
        },
        {
          "fold": 2,
          "train_size": 2190,
          "test_size": 1095,
          "r2": -0.006255839082627723,
          "rmse": 627.3562663646554,
          "mae": 538.6553301433236
        },
        {
          "fold": 3,
          "train_size": 3285,
          "test_size": 1095,
          "r2": -0.0007821615377934243,
          "rmse": 608.5947961924718,
          "mae": 523.6682561188305
        },
        {
          "fold": 4,
          "train_size": 4380,
          "test_size": 1095,
          "r2": -0.0026778960933770968,
          "rmse": 612.1441859906598,
          "mae": 532.2225684165123
        }
      ]
    },
    "medium_clothing": {
      "model_name": "medium_clothing",
      "num_folds": 5,
      "mean_r2": -0.013153525200253535,
      "std_r2": 0.01040298669770052,
      "mean_rmse": 622.8648392684025,
      "mean_mae": 537.5823949154482,
      "fold_r2_scores": [
        -0.02835238028364362,
        -0.016822143593364203,
        -0.00600384127189435,
        -0.001435735652111969
      ],
      "fold_rmse_scores": [
        629.6929469204978,
        631.2089750617121,
        613.5597936018243,
        616.9976414895758
      ],
      "fold_mae_scores": [
        536.5830300481416,
        547.6901804553564,
        529.8569763001061,
        536.1993928581888
      ],
      "weather_elasticity": {
        "temperature": [
          -8.735712373686248,
          -15.886200584147138,
          -6.7805320816272046,
          -4.759551140497592
        ],
        "humidity": [
          6.453741141199333,
          10.350319846647087,
          2.2429154306937864,
          0.26762746127201475
        ],
        "precipitation": [
          20.614710915035698,
          19.217945548657816,
          1.3941102859879964,
          5.971207545678087
        ]
      },
      "channel_roas": {
        "meta_spend": [
          -14.803001099308483,
          -28.102583625201554,
          14.242205549060094,
          38.91926815799174
        ],
        "google_spend": [
          -38.423630464030374,
          -50.46509299240624,
          -45.454201011425454,
          10.095286063600073
        ]
      },
      "fold_details": [
        {
          "fold": 1,
          "train_size": 1095,
          "test_size": 1095,
          "r2": -0.02835238028364362,
          "rmse": 629.6929469204978,
          "mae": 536.5830300481416
        },
        {
          "fold": 2,
          "train_size": 2190,
          "test_size": 1095,
          "r2": -0.016822143593364203,
          "rmse": 631.2089750617121,
          "mae": 547.6901804553564
        },
        {
          "fold": 3,
          "train_size": 3285,
          "test_size": 1095,
          "r2": -0.00600384127189435,
          "rmse": 613.5597936018243,
          "mae": 529.8569763001061
        },
        {
          "fold": 4,
          "train_size": 4380,
          "test_size": 1095,
          "r2": -0.001435735652111969,
          "rmse": 616.9976414895758,
          "mae": 536.1993928581888
        }
      ]
    },
    "medium_footwear": {
      "model_name": "medium_footwear",
      "num_folds": 5,
      "mean_r2": -0.0018751643367260762,
      "std_r2": 0.0038470526488452155,
      "mean_rmse": 605.8378782047014,
      "mean_mae": 520.6714203387955,
      "fold_r2_scores": [
        -0.007330507919754536,
        0.002774231320976539,
        0.00046389158598214575,
        -0.003408272334108453
      ],
      "fold_rmse_scores": [
        603.3256762208923,
        600.437359892504,
        601.2718237216308,
        618.3166529837787
      ],
      "fold_mae_scores": [
        518.8074361655501,
        515.442802351444,
        517.18309274443,
        531.2523500937582
      ],
      "weather_elasticity": {
        "temperature": [
          -24.1167209996811,
          -13.815727603594935,
          -5.421647707467902,
          -1.873514137127205
        ],
        "humidity": [
          21.18947387766669,
          10.02122378822733,
          1.1482555987932168,
          -2.114534688969593
        ],
        "precipitation": [
          6.398459190639448,
          -11.016383551942726,
          -12.96053010899405,
          -13.194434725160068
        ]
      },
      "channel_roas": {
        "meta_spend": [
          -24.300941698928764,
          -34.10978054146161,
          -35.11517322103548,
          -15.288719250262721
        ],
        "google_spend": [
          -15.639957078169736,
          -28.880389918101212,
          -45.89820702414097,
          -10.902076426208502
        ]
      },
      "fold_details": [
        {
          "fold": 1,
          "train_size": 1095,
          "test_size": 1095,
          "r2": -0.007330507919754536,
          "rmse": 603.3256762208923,
          "mae": 518.8074361655501
        },
        {
          "fold": 2,
          "train_size": 2190,
          "test_size": 1095,
          "r2": 0.002774231320976539,
          "rmse": 600.437359892504,
          "mae": 515.442802351444
        },
        {
          "fold": 3,
          "train_size": 3285,
          "test_size": 1095,
          "r2": 0.00046389158598214575,
          "rmse": 601.2718237216308,
          "mae": 517.18309274443
        },
        {
          "fold": 4,
          "train_size": 4380,
          "test_size": 1095,
          "r2": -0.003408272334108453,
          "rmse": 618.3166529837787,
          "mae": 531.2523500937582
        }
      ]
    },
    "medium_sports": {
      "model_name": "medium_sports",
      "num_folds": 5,
      "mean_r2": 0.0003816942232364451,
      "std_r2": 0.003099599427152946,
      "mean_rmse": 606.7419622799773,
      "mean_mae": 518.2483563106489,
      "fold_r2_scores": [
        -0.0033983425810990564,
        -0.0015410628813821159,
        0.004679373329600445,
        0.001786809025826508
      ],
      "fold_rmse_scores": [
        607.1507760096747,
        609.0747750146975,
        602.6157244947531,
        608.1265736007839
      ],
      "fold_mae_scores": [
        516.8585368402938,
        521.6737378454294,
        512.7973697828048,
        521.6637807740674
      ],
      "weather_elasticity": {
        "temperature": [
          3.2410468165192787,
          -0.20048867244670995,
          -0.1305494076331327,
          -2.3227955869237253
        ],
        "humidity": [
          -5.823514266074411,
          -4.343968078004877,
          -4.443297057125498,
          -1.535373014744031
        ],
        "precipitation": [
          -16.594133820732843,
          1.33834281286671,
          2.629170025984378,
          2.249143331626215
        ]
      },
      "channel_roas": {
        "meta_spend": [
          -20.63096994413563,
          -8.014402193625312,
          2.201212014304638,
          -38.683923788359294
        ],
        "google_spend": [
          -33.34414512442849,
          13.607087763467291,
          54.1762766754375,
          6.906296162829763
        ]
      },
      "fold_details": [
        {
          "fold": 1,
          "train_size": 1095,
          "test_size": 1095,
          "r2": -0.0033983425810990564,
          "rmse": 607.1507760096747,
          "mae": 516.8585368402938
        },
        {
          "fold": 2,
          "train_size": 2190,
          "test_size": 1095,
          "r2": -0.0015410628813821159,
          "rmse": 609.0747750146975,
          "mae": 521.6737378454294
        },
        {
          "fold": 3,
          "train_size": 3285,
          "test_size": 1095,
          "r2": 0.004679373329600445,
          "rmse": 602.6157244947531,
          "mae": 512.7973697828048
        },
        {
          "fold": 4,
          "train_size": 4380,
          "test_size": 1095,
          "r2": 0.001786809025826508,
          "rmse": 608.1265736007839,
          "mae": 521.6637807740674
        }
      ]
    },
    "none_books": {
      "model_name": "none_books",
      "num_folds": 5,
      "mean_r2": -0.006282852613853557,
      "std_r2": 0.006191433767958891,
      "mean_rmse": 514.8274161049483,
      "mean_mae": 446.44317683874914,
      "fold_r2_scores": [
        -0.010722762052606027,
        -0.011713351764889524,
        0.003916371470786717,
        -0.006611668108705393
      ],
      "fold_rmse_scores": [
        522.7202745925739,
        517.3240866905089,
        499.13267286811765,
        520.1326302685927
      ],
      "fold_mae_scores": [
        455.16974478881576,
        449.9944386079397,
        429.1849662357669,
        451.4235577224742
      ],
      "weather_elasticity": {
        "temperature": [
          7.798021236668487,
          2.859357845875335,
          2.5535773247078026,
          0.7973395979471662
        ],
        "humidity": [
          -7.248787361145389,
          -3.745807905602646,
          -3.530473019671774,
          -2.025903612563741
        ],
        "precipitation": [
          -10.69848946379181,
          7.471557045974256,
          -6.779498427864219,
          -7.738837332102952
        ]
      },
      "channel_roas": {
        "meta_spend": [
          23.247958246065444,
          -1.9310662813145951,
          -3.4738482385739715,
          -20.79793370248476
        ],
        "google_spend": [
          42.87043910249875,
          -21.8916301302733,
          -2.063649532521102,
          -30.313948783639727
        ]
      },
      "fold_details": [
        {
          "fold": 1,
          "train_size": 1095,
          "test_size": 1095,
          "r2": -0.010722762052606027,
          "rmse": 522.7202745925739,
          "mae": 455.16974478881576
        },
        {
          "fold": 2,
          "train_size": 2190,
          "test_size": 1095,
          "r2": -0.011713351764889524,
          "rmse": 517.3240866905089,
          "mae": 449.9944386079397
        },
        {
          "fold": 3,
          "train_size": 3285,
          "test_size": 1095,
          "r2": 0.003916371470786717,
          "rmse": 499.13267286811765,
          "mae": 429.1849662357669
        },
        {
          "fold": 4,
          "train_size": 4380,
          "test_size": 1095,
          "r2": -0.006611668108705393,
          "rmse": 520.1326302685927,
          "mae": 451.4235577224742
        }
      ]
    },
    "none_electronics": {
      "model_name": "none_electronics",
      "num_folds": 5,
      "mean_r2": -0.00522887485043716,
      "std_r2": 0.0016054073271430374,
      "mean_rmse": 512.0346352162658,
      "mean_mae": 444.81515303586906,
      "fold_r2_scores": [
        -0.003414078968487333,
        -0.004949716268879412,
        -0.007816240749014547,
        -0.004735463415367347
      ],
      "fold_rmse_scores": [
        527.7282203830389,
        508.2272047237536,
        509.2028058242776,
        502.9803099339929
      ],
      "fold_mae_scores": [
        463.1744230364963,
        441.43335383374097,
        440.2041391766221,
        434.4486960966167
      ],
      "weather_elasticity": {
        "temperature": [
          1.8214109793997526,
          -2.138968285954143,
          -1.0768523723981156,
          1.8289869572224673
        ],
        "humidity": [
          -3.913397267493239,
          1.854695392551231,
          0.5924149908480538,
          -2.600079476487998
        ],
        "precipitation": [
          10.001195788915592,
          14.776302285473912,
          17.872015007111358,
          9.824953440473806
        ]
      },
      "channel_roas": {
        "meta_spend": [
          0.7787900307500519,
          17.718015720864624,
          1.338227017170106,
          19.452098015064685
        ],
        "google_spend": [
          22.119702435187985,
          15.294350193345357,
          -16.996920004177,
          4.158555283542869
        ]
      },
      "fold_details": [
        {
          "fold": 1,
          "train_size": 1095,
          "test_size": 1095,
          "r2": -0.003414078968487333,
          "rmse": 527.7282203830389,
          "mae": 463.1744230364963
        },
        {
          "fold": 2,
          "train_size": 2190,
          "test_size": 1095,
          "r2": -0.004949716268879412,
          "rmse": 508.2272047237536,
          "mae": 441.43335383374097
        },
        {
          "fold": 3,
          "train_size": 3285,
          "test_size": 1095,
          "r2": -0.007816240749014547,
          "rmse": 509.2028058242776,
          "mae": 440.2041391766221
        },
        {
          "fold": 4,
          "train_size": 4380,
          "test_size": 1095,
          "r2": -0.004735463415367347,
          "rmse": 502.9803099339929,
          "mae": 434.4486960966167
        }
      ]
    },
    "none_home_decor": {
      "model_name": "none_home_decor",
      "num_folds": 5,
      "mean_r2": -0.004561399109602071,
      "std_r2": 0.003283265984720458,
      "mean_rmse": 507.07548022944775,
      "mean_mae": 436.00508144540277,
      "fold_r2_scores": [
        -0.0020976992392556237,
        -0.009296739594843562,
        -0.0009714088812080579,
        -0.0058797487231010415
      ],
      "fold_rmse_scores": [
        507.5933755054805,
        507.6491406920869,
        501.4114636989477,
        511.647941021276
      ],
      "fold_mae_scores": [
        434.14255173742634,
        433.3469784732879,
        434.519977405553,
        442.0108181653437
      ],
      "weather_elasticity": {
        "temperature": [
          0.1560718881427923,
          1.749792343046879,
          2.447849184339297,
          4.840517258382599
        ],
        "humidity": [
          -0.6344452723299043,
          -3.0344477024057785,
          -4.558114299557628,
          -7.732222208173422
        ],
        "precipitation": [
          -7.367117146736132,
          -4.4236074861917025,
          4.997964047736866,
          11.36974675358802
        ]
      },
      "channel_roas": {
        "meta_spend": [
          21.595297931425684,
          14.416747274302836,
          -30.24106705565018,
          -26.492212770672207
        ],
        "google_spend": [
          3.52264902351405,
          8.191248249973608,
          -14.392708782110516,
          -3.112928957890661
        ]
      },
      "fold_details": [
        {
          "fold": 1,
          "train_size": 1095,
          "test_size": 1095,
          "r2": -0.0020976992392556237,
          "rmse": 507.5933755054805,
          "mae": 434.14255173742634
        },
        {
          "fold": 2,
          "train_size": 2190,
          "test_size": 1095,
          "r2": -0.009296739594843562,
          "rmse": 507.6491406920869,
          "mae": 433.3469784732879
        },
        {
          "fold": 3,
          "train_size": 3285,
          "test_size": 1095,
          "r2": -0.0009714088812080579,
          "rmse": 501.4114636989477,
          "mae": 434.519977405553
        },
        {
          "fold": 4,
          "train_size": 4380,
          "test_size": 1095,
          "r2": -0.0058797487231010415,
          "rmse": 511.647941021276,
          "mae": 442.0108181653437
        }
      ]
    },
    "none_kitchen": {
      "model_name": "none_kitchen",
      "num_folds": 5,
      "mean_r2": -0.007223458938208249,
      "std_r2": 0.004785189843540072,
      "mean_rmse": 513.882381378903,
      "mean_mae": 444.3555553162201,
      "fold_r2_scores": [
        -0.009670276126838129,
        -0.013333561742488786,
        -0.005359689070826512,
        -0.0005303088126795696
      ],
      "fold_rmse_scores": [
        527.8905481131582,
        510.0989959945674,
        516.7649968652642,
        500.7749845426225
      ],
      "fold_mae_scores": [
        461.11275768329676,
        437.8303477878421,
        447.16092734331613,
        431.31818845042545
      ],
      "weather_elasticity": {
        "temperature": [
          -4.483131423974586,
          2.12978913165467,
          3.474963586885272,
          0.7759022846528485
        ],
        "humidity": [
          5.590078931319193,
          -3.928278856835142,
          -3.494161900757662,
          -0.5634617265325766
        ],
        "precipitation": [
          -15.69638571758488,
          -4.355741491539618,
          -12.232365196727427,
          -8.02612546151663
        ]
      },
      "channel_roas": {
        "meta_spend": [
          -7.906660663611423,
          -52.83072494665036,
          15.589446675141271,
          -2.7671568030698426
        ],
        "google_spend": [
          45.36497976494034,
          -26.674524961063725,
          44.44645698068142,
          8.056666052618239
        ]
      },
      "fold_details": [
        {
          "fold": 1,
          "train_size": 1095,
          "test_size": 1095,
          "r2": -0.009670276126838129,
          "rmse": 527.8905481131582,
          "mae": 461.11275768329676
        },
        {
          "fold": 2,
          "train_size": 2190,
          "test_size": 1095,
          "r2": -0.013333561742488786,
          "rmse": 510.0989959945674,
          "mae": 437.8303477878421
        },
        {
          "fold": 3,
          "train_size": 3285,
          "test_size": 1095,
          "r2": -0.005359689070826512,
          "rmse": 516.7649968652642,
          "mae": 447.16092734331613
        },
        {
          "fold": 4,
          "train_size": 4380,
          "test_size": 1095,
          "r2": -0.0005303088126795696,
          "rmse": 500.7749845426225,
          "mae": 431.31818845042545
        }
      ]
    },
    "none_office_supplies": {
      "model_name": "none_office_supplies",
      "num_folds": 5,
      "mean_r2": -0.005041395236690782,
      "std_r2": 0.004936211910041867,
      "mean_rmse": 517.1631978971545,
      "mean_mae": 446.713443129603,
      "fold_r2_scores": [
        -3.771171119404393e-05,
        -0.00612097745522977,
        -0.01264095952473454,
        -0.0013659322556047737
      ],
      "fold_rmse_scores": [
        515.2918038551193,
        507.08271147912114,
        523.6676877138635,
        522.6105885405142
      ],
      "fold_mae_scores": [
        443.28947471724905,
        437.28271331982313,
        452.81263048922114,
        453.4689539921184
      ],
      "weather_elasticity": {
        "temperature": [
          -5.701780738394706,
          -5.722320464125374,
          -4.230517617623966,
          -0.34334537354917255
        ],
        "humidity": [
          9.110401573305243,
          10.257911449511322,
          6.943071988877117,
          0.7210910214582809
        ],
        "precipitation": [
          -6.82013771676539,
          -20.504815622048024,
          -12.842427917983017,
          -8.370205884926454
        ]
      },
      "channel_roas": {
        "meta_spend": [
          14.918271223744725,
          12.952168308376626,
          21.278157953001436,
          25.8020305402155
        ],
        "google_spend": [
          2.3390378445630695,
          1.5047661470805302,
          -8.36269005206118,
          -16.558236200588873
        ]
      },
      "fold_details": [
        {
          "fold": 1,
          "train_size": 1095,
          "test_size": 1095,
          "r2": -3.771171119404393e-05,
          "rmse": 515.2918038551193,
          "mae": 443.28947471724905
        },
        {
          "fold": 2,
          "train_size": 2190,
          "test_size": 1095,
          "r2": -0.00612097745522977,
          "rmse": 507.08271147912114,
          "mae": 437.28271331982313
        },
        {
          "fold": 3,
          "train_size": 3285,
          "test_size": 1095,
          "r2": -0.01264095952473454,
          "rmse": 523.6676877138635,
          "mae": 452.81263048922114
        },
        {
          "fold": 4,
          "train_size": 4380,
          "test_size": 1095,
          "r2": -0.0013659322556047737,
          "rmse": 522.6105885405142,
          "mae": 453.4689539921184
        }
      ]
    }
  }
}