{
  "critic": "managerselfcheck",
  "code": 0,
  "stdout": "manager_self_check critic retired from active exit criteria on 2025-10-17; no action required.",
  "stderr": "",
  "passed": true,
  "analysis": null,
  "git_sha": "a9b2c543d3f630fb4a1c37dbcf74548b8853b762",
  "timestamp": "2025-10-17T17:16:12.380Z",
  "identity": {
    "title": "Manager Self Check",
    "mission": "Safeguard manager_self_check discipline.",
    "powers": [
      "Reports on findings when configuration is missing."
    ],
    "authority": "advisory",
    "domain": "manager_self_check"
  }
}
